apt_mirror_updater/__init__.py
apt_mirror_updater/cli.py
apt_mirror_updater/http.py
apt_mirror_updater/releases.py
apt_mirror_updater/tests.py
apt_mirror_updater/backends/__init__.py
apt_mirror_updater/backends/debian.py
apt_mirror_updater/backends/elementary.py
apt_mirror_updater/backends/ubuntu.py
apt_mirror_updater-7.3.dist-info/LICENSE.txt
apt_mirror_updater-7.3.dist-info/METADATA
apt_mirror_updater-7.3.dist-info/WHEEL
apt_mirror_updater-7.3.dist-info/entry_points.txt
apt_mirror_updater-7.3.dist-info/top_level.txt
apt_mirror_updater-7.3.dist-info/RECORD
