Metadata-Version: 2.1
Name: apt-mirror-updater
Version: 7.3
Summary: Automated, robust apt-get mirror selection for Debian and Ubuntu
Home-page: https://apt-mirror-updater.readthedocs.io
Author: Peter Odding
Author-email: peter@peterodding.com
License: MIT
Platform: UNKNOWN
Classifier: Development Status :: 4 - Beta
Classifier: Environment :: Console
Classifier: Intended Audience :: Developers
Classifier: Intended Audience :: Information Technology
Classifier: Intended Audience :: System Administrators
Classifier: License :: OSI Approved :: MIT License
Classifier: Natural Language :: English
Classifier: Operating System :: POSIX :: Linux
Classifier: Programming Language :: Python
Classifier: Programming Language :: Python :: 2
Classifier: Programming Language :: Python :: 2.7
Classifier: Programming Language :: Python :: 3
Classifier: Programming Language :: Python :: 3.5
Classifier: Programming Language :: Python :: 3.6
Classifier: Programming Language :: Python :: 3.7
Classifier: Programming Language :: Python :: 3.8
Classifier: Programming Language :: Python :: Implementation :: CPython
Classifier: Programming Language :: Python :: Implementation :: PyPy
Classifier: Topic :: Software Development
Classifier: Topic :: Software Development :: Libraries :: Python Modules
Classifier: Topic :: System :: Shells
Classifier: Topic :: System :: System Shells
Classifier: Topic :: System :: Systems Administration
Classifier: Topic :: Terminals
Classifier: Topic :: Utilities
Requires-Python: >=2.7, !=3.0.*, !=3.1.*, !=3.2.*, !=3.3.*, !=3.4.*
Requires-Dist: beautifulsoup4 (>=4.9.3)
Requires-Dist: capturer (>=3.0)
Requires-Dist: coloredlogs (>=10.0)
Requires-Dist: executor (>=21.3)
Requires-Dist: flufl.enum (>=4.0.1)
Requires-Dist: humanfriendly (>=8.1)
Requires-Dist: property-manager (>=3.0)
Requires-Dist: six (>=1.10.0)
Requires-Dist: stopit (>=1.1.1)
